_cy_deblend.cpython-37m-darwin.so
cy_deblend.cpython-37m-darwin.so
deepscan/SB.py
deepscan/__init__.py
deepscan/_cy_deblend.cpython-37m-darwin.so
deepscan/convolution.py
deepscan/cy_deblend.cpython-37m-darwin.so
deepscan/cy_skymap.cpython-37m-darwin.so
deepscan/cython.cpython-37m-darwin.so
deepscan/dbscan.py
deepscan/deblend.py
deepscan/deepscan.py
deepscan/geometry.py
deepscan/makecat.py
deepscan/masking.py
deepscan/minpts.py
deepscan/remote_data.py
deepscan/sersic.py
deepscan/sextractor.py
deepscan/skymap.py
deepscan/source.py
deepscan/utils.py
deepscan/cython/cy_dbscan.cpython-37m-darwin.so
deepscan/cython/cy_deblend.cpython-37m-darwin.so
deepscan/cython/cy_makecat.cpython-37m-darwin.so
deepscan/cython/cy_skymap.cpython-37m-darwin.so
deepscan/src/cy_deblend.cpython-37m-darwin.so
deepscan/src/cy_skymap.cpython-37m-darwin.so
deepscan-0.65.dist-info/LICENSE.md
deepscan-0.65.dist-info/METADATA
deepscan-0.65.dist-info/WHEEL
deepscan-0.65.dist-info/top_level.txt
deepscan-0.65.dist-info/RECORD
